konbini/__init__.py
konbini/cli/__init__.py
konbini/cli/dataset.py
konbini/cli/kon.py
konbini-0.1.0.dist-info/WHEEL
konbini-0.1.0.dist-info/entry_points.txt
konbini-0.1.0.dist-info/METADATA
konbini-0.1.0.dist-info/RECORD
